pyquery_polars/__init__.py
pyquery_polars/api/auth.py
pyquery_polars/api/db.py
pyquery_polars/api/dependencies.py
pyquery_polars/api/main.py
pyquery_polars/api/routes/datasets.py
pyquery_polars/api/routes/files.py
pyquery_polars/api/routes/meta.py
pyquery_polars/api/routes/recipes.py
pyquery_polars/backend/__init__.py
pyquery_polars/backend/analysis/__init__.py
pyquery_polars/backend/analysis/inference.py
pyquery_polars/backend/analysis/joins.py
pyquery_polars/backend/analysis/ml.py
pyquery_polars/backend/analysis/stats.py
pyquery_polars/backend/engine/__init__.py
pyquery_polars/backend/engine/core.py
pyquery_polars/backend/engine/jobs.py
pyquery_polars/backend/engine/registry.py
pyquery_polars/backend/io/__init__.py
pyquery_polars/backend/io/files.py
pyquery_polars/backend/io/plugins.py
pyquery_polars/backend/processing/__init__.py
pyquery_polars/backend/processing/executor.py
pyquery_polars/backend/processing/materializer.py
pyquery_polars/backend/processing/transforms/analytics.py
pyquery_polars/backend/processing/transforms/cleaning.py
pyquery_polars/backend/processing/transforms/columns.py
pyquery_polars/backend/processing/transforms/combine.py
pyquery_polars/backend/processing/transforms/rows.py
pyquery_polars/backend/processing/transforms/scientific.py
pyquery_polars/backend/utils/helpers.py
pyquery_polars/backend/utils/parsing.py
pyquery_polars/cli/branding.py
pyquery_polars/cli/headless.py
pyquery_polars/cli/interactive.py
pyquery_polars/cli/main.py
pyquery_polars/core/io_params.py
pyquery_polars/core/models.py
pyquery_polars/core/params.py
pyquery_polars/core/registry.py
pyquery_polars/frontend/app.py
pyquery_polars/frontend/components/eda/__init__.py
pyquery_polars/frontend/components/eda/contrast.py
pyquery_polars/frontend/components/eda/core.py
pyquery_polars/frontend/components/eda/ml.py
pyquery_polars/frontend/components/eda/overview.py
pyquery_polars/frontend/components/eda/plots.py
pyquery_polars/frontend/components/eda/profiling.py
pyquery_polars-2.4.0.dist-info/WHEEL
pyquery_polars-2.4.0.dist-info/entry_points.txt
pyquery_polars-2.4.0.dist-info/METADATA
pyquery_polars-2.4.0.dist-info/RECORD
