Metadata-Version: 2.3
Name: pyquery-polars
Version: 2.4.0
Summary: Enterprise-grade Headless ETL Engine with Interactive UI
Keywords: PyQuery,Polars,ETL,Big Data,Excel,Power BI,Automation,Analytics,Audit
Author: Shan
Author-email: Shan <tksudharshan@gmail.com>
Classifier: Intended Audience :: Developers
Classifier: Intended Audience :: Financial and Insurance Industry
Classifier: Intended Audience :: Information Technology
Classifier: Topic :: Office/Business :: Financial :: Spreadsheet
Classifier: Topic :: Software Development :: Libraries :: Python Modules
Classifier: Topic :: Utilities
Classifier: License :: OSI Approved :: GNU General Public License v3 (GPLv3)
Classifier: Programming Language :: Python :: 3
Classifier: Programming Language :: Python :: 3.10
Classifier: Programming Language :: Python :: 3.11
Classifier: Programming Language :: Python :: 3.12
Classifier: Programming Language :: Python :: 3.13
Classifier: Operating System :: Microsoft :: Windows
Classifier: Operating System :: MacOS
Classifier: Natural Language :: English
Requires-Dist: polars>=1.0.0
Requires-Dist: streamlit>=1.30.0
Requires-Dist: fastapi>=0.109.0
Requires-Dist: uvicorn>=0.25.0
Requires-Dist: pydantic>=2.5.0
Requires-Dist: rich>=13.7.0
Requires-Dist: questionary>=2.0.0
Requires-Dist: xlsxwriter>=3.1.0
Requires-Dist: openpyxl>=3.1.0
Requires-Dist: pyarrow>=14.0.0
Requires-Dist: connectorx>=0.3.3
Requires-Dist: fastexcel>=0.16.0
Requires-Dist: python-multipart>=0.0.20
Requires-Dist: matplotlib>=3.9.4
Requires-Dist: seaborn>=0.13.2
Requires-Dist: plotly>=6.5.0
Requires-Dist: statsmodels>=0.14.6
Requires-Dist: scikit-learn>=1.6.1
Requires-Dist: scipy>=1.13.1
Requires-Dist: chardet>=5.2.0
Requires-Python: >=3.9
Project-URL: Changelog, https://github.com/tks18/pyquery/releases
Project-URL: Documentation, https://github.com/tks18/pyquery#readme
Project-URL: Homepage, https://github.com/tks18/pyquery
Project-URL: Issues, https://github.com/tks18/pyquery/issues
Project-URL: Repository, https://github.com/tks18/pyquery
